[
  {
    "id": 1,
    "wpm": 0
  },
  {
    "id": 2,
    "wpm": 0
  },
  {
    "id": 3,
    "wpm": 0
  },
  {
    "id": 4,
    "wpm": 0
  },
  {
    "id": 5,
    "wpm": 0
  },
  {
    "id": 6,
    "wpm": 0
  },
  {
    "id": 7,
    "wpm": 0
  },
  {
    "id": 8,
    "wpm": 0
  },
  {
    "id": 9,
    "wpm": 0
  },
  {
    "id": 10,
    "wpm": 0
  },
  {
    "id": 11,
    "wpm": 0
  },
  {
    "id": 12,
    "wpm": 0
  },
  {
    "id": 13,
    "wpm": 0
  },
  {
    "id": 14,
    "wpm": 0
  },
  {
    "id": 15,
    "wpm": 0
  },
  {
    "id": 16,
    "wpm": 0
  },
  {
    "id": 17,
    "wpm": 0
  },
  {
    "id": 18,
    "wpm": 0
  },
  {
    "id": 19,
    "wpm": 0
  },
  {
    "id": 20,
    "wpm": 0
  },
  {
    "id": 21,
    "wpm": 0
  },
  {
    "id": 22,
    "wpm": 0
  },
  {
    "id": 23,
    "wpm": 0
  },
  {
    "id": 24,
    "wpm": 0
  },
  {
    "id": 25,
    "wpm": 0
  },
  {
    "id": 26,
    "wpm": 0
  },
  {
    "id": 27,
    "wpm": 0
  },
  {
    "id": 28,
    "wpm": 0
  },
  {
    "id": 29,
    "wpm": 0
  },
  {
    "id": 30,
    "wpm": 0
  },
  {
    "id": 31,
    "wpm": 0
  },
  {
    "id": 32,
    "wpm": 0
  },
  {
    "id": 33,
    "wpm": 0
  },
  {
    "id": 34,
    "wpm": 0
  },
  {
    "id": 35,
    "wpm": 0
  },
  {
    "id": 36,
    "wpm": 0
  },
  {
    "id": 37,
    "wpm": 0
  },
  {
    "id": 38,
    "wpm": 0
  },
  {
    "id": 39,
    "wpm": 0
  },
  {
    "id": 40,
    "wpm": 0
  },
  {
    "id": 41,
    "wpm": 0
  },
  {
    "id": 42,
    "wpm": 0
  },
  {
    "id": 43,
    "wpm": 0
  },
  {
    "id": 44,
    "wpm": 0
  },
  {
    "id": 45,
    "wpm": 0
  },
  {
    "id": 46,
    "wpm": 0
  },
  {
    "id": 47,
    "wpm": 0
  },
  {
    "id": 48,
    "wpm": 0
  },
  {
    "id": 49,
    "wpm": 0,
    "info": "config purpose object",
    "lastLevel": 1,
    "lastBackup": "",
    "newUser": true
  }
]
